Metadata-Version: 1.0
Name: sanne
Version: 0.0
Summary: Usefull Functions Sanne
Home-page: UNKNOWN
Author: UNKNOWN
Author-email: sanne.klein@klm.com
License: UNKNOWN
Platform: UNKNOWN
